LICENSE.txt
MANIFEST.in
setup.py
nutch/__init__.py
nutch/crawl.py
nutch/nutch.py
nutch/test_nutch.py
nutch.egg-info/PKG-INFO
nutch.egg-info/SOURCES.txt
nutch.egg-info/dependency_links.txt
nutch.egg-info/entry_points.txt
nutch.egg-info/requires.txt
nutch.egg-info/top_level.txt
nutch.egg-info/zip-safe