Metadata-Version: 1.1
Name: nutch
Version: 1.10.3
Summary: Apache Nutch Python library
Home-page: http://github.com/chrismattmann/nutch-python
Author: Chris Mattmann
Author-email: chris.a.mttmnn@nasa.gov
License: 
